{
  "registration_no": "MAL17126049NCR",
  "product_name": "VitaHealth Crowning Glory Gold Tablet",
  "holder": "VITAHEALTH BIOTECH SDN BHD",
  "holder_address": "NO.23, JALAN JURUNILAI U1/20, SEKSYEN U1, HICOM GLENMARIE INDUSTRIAL PARK, 40150, SHAH ALAM, MALAYSIA,",
  "manufacturer": "ARNET PHARMACEUTICAL CORPORATION",
  "manufacturer_address": "2525, DAVIE ROAD STE, SUITE 330, DAVIE, FLORIDA, 33317, UNITED STATES,",
  "importer": "VITAHEALTH MALAYSIA SDN. BHD.",
  "importer_address": "NO. 23, JALAN JURUNILAI U1/20, HICOM GLENMARIE INDUSTRIAL PARK, SEKSYEN U1, 40150, SHAH ALAM, MALAYSIA,",
  "active_ingredients": [
    "FOLIC  ACID",
    "MANGANESE SULPHATE MONOHYDRATE",
    "RETINYL ACETATE",
    "TOCOPHERYL ACETATE, DL-ALPHA",
    "LINUM USITATISSIMUM SEED (FLAXSEED) EXTRACT*",
    "METHYLSULFONYLMETHANE",
    "L-METHIONINE",
    "L-CYSTEINE HCL",
    "ASCORBIC ACID (VITAMIN C)",
    "BIOTIN",
    "SACCHAROMYCES CEREVISIAE",
    "EQUISETUM ARVENSE EXTRACT (HORSETAIL)",
    "NIACINAMIDE",
    "L-LYSINE HYDROCHLORIDE",
    "PARA AMINO BENZOIC ACID (PABA)",
    "CHOLINE BITARTRATE",
    "INOSITOL",
    "PYRIDOXINE HYDROCHLORIDE",
    "L-ARGININE",
    "VITIS VINIFERA (GRAPE SEED EXTRACT)",
    "FERROUS FUMARATE",
    "D-CALCIUM PANTOTHENATE",
    "ZINC OXIDE",
    "THIAMINE MONONITRATE",
    "POTASSIUM IODIDE",
    "SODIUM SELENATE",
    "RIBOFLAVIN",
    "CUPRIC OXIDE",
    "CYANOCOBALAMIN"
  ],
  "sku": [
    {
      "package_description": "10 Tablets",
      "sku_unit": "Tablets",
      "quantity_per_sku": 10,
      "base_cost": 0,
      "tier_pricing": [
        {
          "min_qty": 100,
          "cost_per_unit": 0,
          "source": "Placeholder Source",
          "market_type": "Others",
          "custom_market_name": "",
          "last_updated": "2025-03-14",
          "remarks": ""
        },
        {
          "min_qty": 500,
          "cost_per_unit": 0,
          "source": "Placeholder Source",
          "market_type": "Others",
          "custom_market_name": "",
          "last_updated": "2025-03-14",
          "remarks": ""
        }
      ],
      "highest_selling_price": 0,
      "lowest_selling_price": 0,
      "price_sources": [
        {
          "reseller_name": "Placeholder Reseller",
          "price": 0,
          "last_updated": "2025-03-14"
        }
      ]
    },
    {
      "package_description": "30 Tablets",
      "sku_unit": "Tablets",
      "quantity_per_sku": 30,
      "base_cost": 0,
      "tier_pricing": [
        {
          "min_qty": 100,
          "cost_per_unit": 0,
          "source": "Placeholder Source",
          "market_type": "Others",
          "custom_market_name": "",
          "last_updated": "2025-03-14",
          "remarks": ""
        },
        {
          "min_qty": 500,
          "cost_per_unit": 0,
          "source": "Placeholder Source",
          "market_type": "Others",
          "custom_market_name": "",
          "last_updated": "2025-03-14",
          "remarks": ""
        }
      ],
      "highest_selling_price": 0,
      "lowest_selling_price": 0,
      "price_sources": [
        {
          "reseller_name": "Placeholder Reseller",
          "price": 0,
          "last_updated": "2025-03-14"
        }
      ]
    },
    {
      "package_description": "60 Tablets",
      "sku_unit": "Tablets",
      "quantity_per_sku": 60,
      "base_cost": 0,
      "tier_pricing": [
        {
          "min_qty": 100,
          "cost_per_unit": 0,
          "source": "Placeholder Source",
          "market_type": "Others",
          "custom_market_name": "",
          "last_updated": "2025-03-14",
          "remarks": ""
        },
        {
          "min_qty": 500,
          "cost_per_unit": 0,
          "source": "Placeholder Source",
          "market_type": "Others",
          "custom_market_name": "",
          "last_updated": "2025-03-14",
          "remarks": ""
        }
      ],
      "highest_selling_price": 0,
      "lowest_selling_price": 0,
      "price_sources": [
        {
          "reseller_name": "Placeholder Reseller",
          "price": 0,
          "last_updated": "2025-03-14"
        }
      ]
    },
    {
      "package_description": "90 Tablets",
      "sku_unit": "Tablets",
      "quantity_per_sku": 90,
      "base_cost": 0,
      "tier_pricing": [
        {
          "min_qty": 100,
          "cost_per_unit": 0,
          "source": "Placeholder Source",
          "market_type": "Others",
          "custom_market_name": "",
          "last_updated": "2025-03-14",
          "remarks": ""
        },
        {
          "min_qty": 500,
          "cost_per_unit": 0,
          "source": "Placeholder Source",
          "market_type": "Others",
          "custom_market_name": "",
          "last_updated": "2025-03-14",
          "remarks": ""
        }
      ],
      "highest_selling_price": 0,
      "lowest_selling_price": 0,
      "price_sources": [
        {
          "reseller_name": "Placeholder Reseller",
          "price": 0,
          "last_updated": "2025-03-14"
        }
      ]
    },
    {
      "package_description": "100 Tablets",
      "sku_unit": "Tablets",
      "quantity_per_sku": 100,
      "base_cost": 0,
      "tier_pricing": [
        {
          "min_qty": 100,
          "cost_per_unit": 0,
          "source": "Placeholder Source",
          "market_type": "Others",
          "custom_market_name": "",
          "last_updated": "2025-03-14",
          "remarks": ""
        },
        {
          "min_qty": 500,
          "cost_per_unit": 0,
          "source": "Placeholder Source",
          "market_type": "Others",
          "custom_market_name": "",
          "last_updated": "2025-03-14",
          "remarks": ""
        }
      ],
      "highest_selling_price": 0,
      "lowest_selling_price": 0,
      "price_sources": [
        {
          "reseller_name": "Placeholder Reseller",
          "price": 0,
          "last_updated": "2025-03-14"
        }
      ]
    },
    {
      "package_description": "120 Tablets",
      "sku_unit": "Tablets",
      "quantity_per_sku": 120,
      "base_cost": 0,
      "tier_pricing": [
        {
          "min_qty": 100,
          "cost_per_unit": 0,
          "source": "Placeholder Source",
          "market_type": "Others",
          "custom_market_name": "",
          "last_updated": "2025-03-14",
          "remarks": ""
        },
        {
          "min_qty": 500,
          "cost_per_unit": 0,
          "source": "Placeholder Source",
          "market_type": "Others",
          "custom_market_name": "",
          "last_updated": "2025-03-14",
          "remarks": ""
        }
      ],
      "highest_selling_price": 0,
      "lowest_selling_price": 0,
      "price_sources": [
        {
          "reseller_name": "Placeholder Reseller",
          "price": 0,
          "last_updated": "2025-03-14"
        }
      ]
    },
    {
      "package_description": "150 Tablets",
      "sku_unit": "Tablets",
      "quantity_per_sku": 150,
      "base_cost": 0,
      "tier_pricing": [
        {
          "min_qty": 100,
          "cost_per_unit": 0,
          "source": "Placeholder Source",
          "market_type": "Others",
          "custom_market_name": "",
          "last_updated": "2025-03-14",
          "remarks": ""
        },
        {
          "min_qty": 500,
          "cost_per_unit": 0,
          "source": "Placeholder Source",
          "market_type": "Others",
          "custom_market_name": "",
          "last_updated": "2025-03-14",
          "remarks": ""
        }
      ],
      "highest_selling_price": 0,
      "lowest_selling_price": 0,
      "price_sources": [
        {
          "reseller_name": "Placeholder Reseller",
          "price": 0,
          "last_updated": "2025-03-14"
        }
      ]
    },
    {
      "package_description": "180 Tablets",
      "sku_unit": "Tablets",
      "quantity_per_sku": 180,
      "base_cost": 0,
      "tier_pricing": [
        {
          "min_qty": 100,
          "cost_per_unit": 0,
          "source": "Placeholder Source",
          "market_type": "Others",
          "custom_market_name": "",
          "last_updated": "2025-03-14",
          "remarks": ""
        },
        {
          "min_qty": 500,
          "cost_per_unit": 0,
          "source": "Placeholder Source",
          "market_type": "Others",
          "custom_market_name": "",
          "last_updated": "2025-03-14",
          "remarks": ""
        }
      ],
      "highest_selling_price": 0,
      "lowest_selling_price": 0,
      "price_sources": [
        {
          "reseller_name": "Placeholder Reseller",
          "price": 0,
          "last_updated": "2025-03-14"
        }
      ]
    }
  ],
  "strength": "",
  "form": "",
  "suppliers": [],
  "reseller_prices": {
    "highest_selling_price": 0,
    "lowest_selling_price": 0,
    "price_sources": []
  },
  "supplier_price": {
    "lowest_price": 0,
    "source": "Placeholder Source",
    "market_type": "Others",
    "custom_market_name": "",
    "last_updated": "2025-03-14",
    "remarks": ""
  },
  "price_updated_year": 2025
}