{
  "registration_no": "MAL25026048NC",
  "product_name": "Rainbow Health Q-Nervo Tablet",
  "holder": "RAINBOW HEALTH (M) SDN. BHD.",
  "holder_address": "17-2, JALAN MERBAH 3,, BANDAR PUCHONG JAYA,, 47100, PUCHONG, MALAYSIA,",
  "manufacturer": "NOVA LABORATORIES SDN. BHD.",
  "manufacturer_address": "LOT 708, NOVA AVENUE, BATU 4, SUNGAI PELEK,, 43950, SEPANG, MALAYSIA,",
  "importer": "",
  "importer_address": "",
  "active_ingredients": [
    "THIAMINE MONONITRATE",
    "PYRIDOXINE HYDROCHLORIDE",
    "METHYLCOBALAMIN",
    "CHROMIUM PICOLINATE",
    "ALPHA LIPOIC ACID"
  ],
  "sku": [
    {
      "package_description": "30 Tablets",
      "sku_unit": "Tablets",
      "quantity_per_sku": 30,
      "base_cost": 0,
      "tier_pricing": [
        {
          "min_qty": 100,
          "cost_per_unit": 0,
          "source": "Placeholder Source",
          "market_type": "Others",
          "custom_market_name": "",
          "last_updated": "2025-03-14",
          "remarks": ""
        },
        {
          "min_qty": 500,
          "cost_per_unit": 0,
          "source": "Placeholder Source",
          "market_type": "Others",
          "custom_market_name": "",
          "last_updated": "2025-03-14",
          "remarks": ""
        }
      ],
      "highest_selling_price": 0,
      "lowest_selling_price": 0,
      "price_sources": [
        {
          "reseller_name": "Placeholder Reseller",
          "price": 0,
          "last_updated": "2025-03-14"
        }
      ]
    },
    {
      "package_description": "60 Tablets",
      "sku_unit": "Tablets",
      "quantity_per_sku": 60,
      "base_cost": 0,
      "tier_pricing": [
        {
          "min_qty": 100,
          "cost_per_unit": 0,
          "source": "Placeholder Source",
          "market_type": "Others",
          "custom_market_name": "",
          "last_updated": "2025-03-14",
          "remarks": ""
        },
        {
          "min_qty": 500,
          "cost_per_unit": 0,
          "source": "Placeholder Source",
          "market_type": "Others",
          "custom_market_name": "",
          "last_updated": "2025-03-14",
          "remarks": ""
        }
      ],
      "highest_selling_price": 0,
      "lowest_selling_price": 0,
      "price_sources": [
        {
          "reseller_name": "Placeholder Reseller",
          "price": 0,
          "last_updated": "2025-03-14"
        }
      ]
    }
  ],
  "strength": "",
  "form": "",
  "suppliers": [],
  "reseller_prices": {
    "highest_selling_price": 0,
    "lowest_selling_price": 0,
    "price_sources": []
  },
  "supplier_price": {
    "lowest_price": 0,
    "source": "Placeholder Source",
    "market_type": "Others",
    "custom_market_name": "",
    "last_updated": "2025-03-14",
    "remarks": ""
  },
  "price_updated_year": 2025
}