{
  "registration_no": "MAL09072817TCR",
  "product_name": "Tian Xian Liquid",
  "holder": "TOMBO ENTERPRISE SDN BHD",
  "holder_address": "SUITE 8.05, 8TH FLOOR, WISMA ZELAN \n, NO. 1, JALAN TASIK PERMAISURI 2 \n, BANDAR TUN RAZAK, 56000, KUALA LUMPUR, MALAYSIA,",
  "manufacturer": "JILIN TONGHUA ZHENGUO PHARMACEUTICAL CO., LTD",
  "manufacturer_address": "WANWANCHUAN BOTANICAL GARDEN, 13400, CHINA,",
  "importer": "TOMBO ENTERPRISE SDN BHD",
  "importer_address": "SUITE 8.05, 8TH FLOOR, WISMA ZELAN, NO. 1, JALAN TASIK PERMAISURI 2 , BANDAR TUN RAZAK, 56000, CHERAS, MALAYSIA,",
  "active_ingredients": [
    "Cordyceps sinensis",
    "Rhizoma Dioscorea Opposita",
    "radix astragalus membranaceus",
    "Herba Scutellaria Barbata",
    "Ganoderma Lucidum.",
    "FRUCTUS LYCIUM BARBARUM",
    "Fructus Ligustrum Lucidum",
    "Concha Hyriopsis cumingii(Margarita)",
    "Radix Glycyrrhiza Uralensis",
    "radix panax ginsen"
  ],
  "sku": [
    {
      "package_description": "20ml x 20vials  Vials",
      "sku_unit": "ml",
      "quantity_per_sku": 20,
      "base_cost": 0,
      "tier_pricing": [
        {
          "min_qty": 100,
          "cost_per_unit": 0,
          "source": "Placeholder Source",
          "market_type": "Others",
          "custom_market_name": "",
          "last_updated": "2025-03-14",
          "remarks": ""
        },
        {
          "min_qty": 500,
          "cost_per_unit": 0,
          "source": "Placeholder Source",
          "market_type": "Others",
          "custom_market_name": "",
          "last_updated": "2025-03-14",
          "remarks": ""
        }
      ],
      "highest_selling_price": 0,
      "lowest_selling_price": 0,
      "price_sources": [
        {
          "reseller_name": "Placeholder Reseller",
          "price": 0,
          "last_updated": "2025-03-14"
        }
      ]
    }
  ],
  "strength": "",
  "form": "",
  "suppliers": [],
  "reseller_prices": {
    "highest_selling_price": 0,
    "lowest_selling_price": 0,
    "price_sources": []
  },
  "supplier_price": {
    "lowest_price": 0,
    "source": "Placeholder Source",
    "market_type": "Others",
    "custom_market_name": "",
    "last_updated": "2025-03-14",
    "remarks": ""
  },
  "price_updated_year": 2025
}