{
  "registration_no": "MAL06051486T",
  "product_name": "Ma\"ajun Ubijaga Tongkat Ali Plus 5g",
  "holder": "SYARIKAT ZULKIFLI BAMADHAJ",
  "holder_address": "1-1 &amp; 1-2, JALAN PERINDUSTRIAN 2,, KAWASAN PERINDUSTRIAN BUKIT BAKRI,, 84200, MUAR, MALAYSIA,",
  "manufacturer": "SYARIKAT ZULKIFLI BAMADHAJ",
  "manufacturer_address": "1-1 &amp; 1-2, JALAN PERINDUSTRIAN 2,, KAWASAN PERINDUSTRIAN BUKIT BAKRI,, 84200, MUAR, MALAYSIA,",
  "importer": "",
  "importer_address": "",
  "active_ingredients": [
    "Acorus calamus",
    "Coriandrum sativum",
    "Eurycoma longifolia",
    "Leptospermum flavescens",
    "Piper longum",
    "Trachyspermum ammi",
    "ZINGIBER MINUS RHIZOM",
    "Trigonella Foenum Graecum",
    "Smilax myosotiflora/ubi jaga",
    "Nigella Sativa.",
    "Allomorphia malacensis"
  ],
  "sku": [
    {
      "package_description": "5g x 15  Pills",
      "sku_unit": "g",
      "quantity_per_sku": 5,
      "base_cost": 0,
      "tier_pricing": [
        {
          "min_qty": 100,
          "cost_per_unit": 0,
          "source": "Placeholder Source",
          "market_type": "Others",
          "custom_market_name": "",
          "last_updated": "2025-03-14",
          "remarks": ""
        },
        {
          "min_qty": 500,
          "cost_per_unit": 0,
          "source": "Placeholder Source",
          "market_type": "Others",
          "custom_market_name": "",
          "last_updated": "2025-03-14",
          "remarks": ""
        }
      ],
      "highest_selling_price": 0,
      "lowest_selling_price": 0,
      "price_sources": [
        {
          "reseller_name": "Placeholder Reseller",
          "price": 0,
          "last_updated": "2025-03-14"
        }
      ]
    }
  ],
  "strength": "",
  "form": "",
  "suppliers": [],
  "reseller_prices": {
    "highest_selling_price": 0,
    "lowest_selling_price": 0,
    "price_sources": []
  },
  "supplier_price": {
    "lowest_price": 0,
    "source": "Placeholder Source",
    "market_type": "Others",
    "custom_market_name": "",
    "last_updated": "2025-03-14",
    "remarks": ""
  },
  "price_updated_year": 2025
}