{
  "registration_no": "MAL08111913T",
  "product_name": "DKE Headache & Toothache Capsule",
  "holder": "Dke Inno In Biotech Sdn. Bhd.",
  "holder_address": "30, KOMPLEKS PERNIAGAAN GANGSA, JALAN GANGSA 1,, 05150, ALOR SETAR, MALAYSIA,",
  "manufacturer": "Dke Inno In Biotech Sdn. Bhd.",
  "manufacturer_address": "30, KOMPLEKS PERNIAGAAN GANGSA, JALAN GANGSA 1,, 05150, ALOR SETAR, MALAYSIA,",
  "importer": "",
  "importer_address": "",
  "active_ingredients": [
    "Rhizoma Notopterygium incisum",
    "RHIZOMA LIGUSTICUM SINENSE",
    "Rhizoma Ligusticum chuanxiong.",
    "RHIZOMA GASTRODIA ELATA.",
    "RAMULUS UNCARIA RHYNCHOPHYLLA",
    "ramulus cinnamomum cassia",
    "Radix Saposhnikovia divaricata",
    "radix paeonia lactiflora",
    "radix angelica dahurica",
    "fructus vitex trifolia",
    "Fructus Piper longum.",
    "Rhizoma Pinellia Ternata",
    "Radix Angelica pubescens"
  ],
  "sku": [
    {
      "package_description": "250 Capsules",
      "sku_unit": "Capsules",
      "quantity_per_sku": 250,
      "base_cost": 0,
      "tier_pricing": [
        {
          "min_qty": 100,
          "cost_per_unit": 0,
          "source": "Placeholder Source",
          "market_type": "Others",
          "custom_market_name": "",
          "last_updated": "2025-03-14",
          "remarks": ""
        },
        {
          "min_qty": 500,
          "cost_per_unit": 0,
          "source": "Placeholder Source",
          "market_type": "Others",
          "custom_market_name": "",
          "last_updated": "2025-03-14",
          "remarks": ""
        }
      ],
      "highest_selling_price": 0,
      "lowest_selling_price": 0,
      "price_sources": [
        {
          "reseller_name": "Placeholder Reseller",
          "price": 0,
          "last_updated": "2025-03-14"
        }
      ]
    },
    {
      "package_description": "10 Capsules",
      "sku_unit": "Capsules",
      "quantity_per_sku": 10,
      "base_cost": 0,
      "tier_pricing": [
        {
          "min_qty": 100,
          "cost_per_unit": 0,
          "source": "Placeholder Source",
          "market_type": "Others",
          "custom_market_name": "",
          "last_updated": "2025-03-14",
          "remarks": ""
        },
        {
          "min_qty": 500,
          "cost_per_unit": 0,
          "source": "Placeholder Source",
          "market_type": "Others",
          "custom_market_name": "",
          "last_updated": "2025-03-14",
          "remarks": ""
        }
      ],
      "highest_selling_price": 0,
      "lowest_selling_price": 0,
      "price_sources": [
        {
          "reseller_name": "Placeholder Reseller",
          "price": 0,
          "last_updated": "2025-03-14"
        }
      ]
    }
  ],
  "strength": "",
  "form": "",
  "suppliers": [],
  "reseller_prices": {
    "highest_selling_price": 0,
    "lowest_selling_price": 0,
    "price_sources": []
  },
  "supplier_price": {
    "lowest_price": 0,
    "source": "Placeholder Source",
    "market_type": "Others",
    "custom_market_name": "",
    "last_updated": "2025-03-14",
    "remarks": ""
  },
  "price_updated_year": 2025
}