{
  "registration_no": "MAL14125114NC",
  "product_name": "Dawon Hoganbo HD-1 Tablet",
  "holder": "Old Ivy Ventures Sdn. Bhd.",
  "holder_address": "A-16-1, BLOK A, SUNWAY GIZA, NO.2, JALAN PJU 5/14, KOTA DAMANSARA, 47810, PETALING JAYA, MALAYSIA,",
  "manufacturer": "CosmaxBio Inc",
  "manufacturer_address": "30, BIO VALLEY 3RO,, JAECHEON-SI,, CHUNGCHEONGBUK-DO,, KOREA,SOUTH,",
  "importer": "Old Ivy Ventures Sdn. Bhd.",
  "importer_address": "A-16-1, BLOK A, SUNWAY GIZA, NO.2, JALAN PJU 5/14, KOTA DAMANSARA, 47810, PETALING JAYA, MALAYSIA,",
  "active_ingredients": [
    "CHITOSAN OLIGOMER",
    "HOVENIA DULCIS BERRY EXTRACT"
  ],
  "sku": [
    {
      "package_description": "120tablet Tablets",
      "sku_unit": "Units",
      "quantity_per_sku": 120,
      "base_cost": 0,
      "tier_pricing": [
        {
          "min_qty": 100,
          "cost_per_unit": 0,
          "source": "Placeholder Source",
          "market_type": "Others",
          "custom_market_name": "",
          "last_updated": "2025-03-14",
          "remarks": ""
        },
        {
          "min_qty": 500,
          "cost_per_unit": 0,
          "source": "Placeholder Source",
          "market_type": "Others",
          "custom_market_name": "",
          "last_updated": "2025-03-14",
          "remarks": ""
        }
      ],
      "highest_selling_price": 0,
      "lowest_selling_price": 0,
      "price_sources": [
        {
          "reseller_name": "Placeholder Reseller",
          "price": 0,
          "last_updated": "2025-03-14"
        }
      ]
    },
    {
      "package_description": "240tablet Tablets",
      "sku_unit": "Units",
      "quantity_per_sku": 240,
      "base_cost": 0,
      "tier_pricing": [
        {
          "min_qty": 100,
          "cost_per_unit": 0,
          "source": "Placeholder Source",
          "market_type": "Others",
          "custom_market_name": "",
          "last_updated": "2025-03-14",
          "remarks": ""
        },
        {
          "min_qty": 500,
          "cost_per_unit": 0,
          "source": "Placeholder Source",
          "market_type": "Others",
          "custom_market_name": "",
          "last_updated": "2025-03-14",
          "remarks": ""
        }
      ],
      "highest_selling_price": 0,
      "lowest_selling_price": 0,
      "price_sources": [
        {
          "reseller_name": "Placeholder Reseller",
          "price": 0,
          "last_updated": "2025-03-14"
        }
      ]
    }
  ],
  "strength": "",
  "form": "",
  "suppliers": [],
  "reseller_prices": {
    "highest_selling_price": 0,
    "lowest_selling_price": 0,
    "price_sources": []
  },
  "supplier_price": {
    "lowest_price": 0,
    "source": "Placeholder Source",
    "market_type": "Others",
    "custom_market_name": "",
    "last_updated": "2025-03-14",
    "remarks": ""
  },
  "price_updated_year": 2025
}