{
  "registration_no": "MAL19950920TR",
  "product_name": "HAPPY LINK 33 LYOPHILIZED ROYAL JELLY (SACHET)",
  "holder": "HAPPY LINK DISTRIBUTORS SDN BHD",
  "holder_address": "NO. 7, JLN TPP 5/11,, TMN PERINDUSTRIAN PUCHONG, 47160, PUCHONG, MALAYSIA,",
  "manufacturer": "HUA FENG (WU XI) NUTRITIONAL FTY",
  "manufacturer_address": "214073,ZHONGGIAO, WU XI,JIANGSU,, CHINA,",
  "importer": "HAPPY LINK DISTRIBUTORS SDN BHD",
  "importer_address": "NO. 7, JLN TPP 5/11,, TMN PERINDUSTRIAN PUCHONG, 47160, PUCHONG, MALAYSIA,",
  "active_ingredients": [
    "ROYAL JELLY"
  ],
  "sku": [
    {
      "package_description": "33Units Units",
      "sku_unit": "Units",
      "quantity_per_sku": 33,
      "base_cost": 0,
      "tier_pricing": [
        {
          "min_qty": 100,
          "cost_per_unit": 0,
          "source": "Placeholder Source",
          "market_type": "Others",
          "custom_market_name": "",
          "last_updated": "2025-03-14",
          "remarks": ""
        },
        {
          "min_qty": 500,
          "cost_per_unit": 0,
          "source": "Placeholder Source",
          "market_type": "Others",
          "custom_market_name": "",
          "last_updated": "2025-03-14",
          "remarks": ""
        }
      ],
      "highest_selling_price": 0,
      "lowest_selling_price": 0,
      "price_sources": [
        {
          "reseller_name": "Placeholder Reseller",
          "price": 0,
          "last_updated": "2025-03-14"
        }
      ]
    }
  ],
  "strength": "",
  "form": "",
  "suppliers": [],
  "reseller_prices": {
    "highest_selling_price": 0,
    "lowest_selling_price": 0,
    "price_sources": []
  },
  "supplier_price": {
    "lowest_price": 0,
    "source": "Placeholder Source",
    "market_type": "Others",
    "custom_market_name": "",
    "last_updated": "2025-03-14",
    "remarks": ""
  },
  "price_updated_year": 2025
}