{
  "registration_no": "MAL13035045AZ",
  "product_name": "DIPHERELINE P.R. POWDER AND SOLVENT FOR SUSPENSION FOR INJECTION 11.25 mg/vial",
  "holder": "ZUELLIG PHARMA SDN. BHD.",
  "holder_address": "NO. 15, PERSIARAN PASAK BUMI, SEK. U8, PERINDUSTRIAN BUKIT JELUTONG, 40150, SHAH ALAM, MALAYSIA,",
  "manufacturer": "IPSEN PHARMA BIOTECH",
  "manufacturer_address": "CHEMIN DEPARTEMENTAL 402 83870 SIGNES, FRANCE,",
  "importer": "ZUELLIG PHARMA SDN. BHD.",
  "importer_address": "NO. 15, PERSIARAN PASAK BUMI,, SEKSYEN U8,, PERINDUSTRIAN BUKIT JELUTONG,, 40150, SHAH ALAM, MALAYSIA,",
  "active_ingredients": [
    "TRIPTORELINE PAMOATE"
  ],
  "sku": [
    {
      "package_description": "1ampoule Ampoules",
      "sku_unit": "Units",
      "quantity_per_sku": 1,
      "base_cost": 0,
      "tier_pricing": [
        {
          "min_qty": 100,
          "cost_per_unit": 0,
          "source": "Placeholder Source",
          "market_type": "Others",
          "custom_market_name": "",
          "last_updated": "2025-03-14",
          "remarks": ""
        },
        {
          "min_qty": 500,
          "cost_per_unit": 0,
          "source": "Placeholder Source",
          "market_type": "Others",
          "custom_market_name": "",
          "last_updated": "2025-03-14",
          "remarks": ""
        }
      ],
      "highest_selling_price": 0,
      "lowest_selling_price": 0,
      "price_sources": [
        {
          "reseller_name": "Placeholder Reseller",
          "price": 0,
          "last_updated": "2025-03-14"
        }
      ]
    },
    {
      "package_description": "1vial Vials",
      "sku_unit": "Units",
      "quantity_per_sku": 1,
      "base_cost": 0,
      "tier_pricing": [
        {
          "min_qty": 100,
          "cost_per_unit": 0,
          "source": "Placeholder Source",
          "market_type": "Others",
          "custom_market_name": "",
          "last_updated": "2025-03-14",
          "remarks": ""
        },
        {
          "min_qty": 500,
          "cost_per_unit": 0,
          "source": "Placeholder Source",
          "market_type": "Others",
          "custom_market_name": "",
          "last_updated": "2025-03-14",
          "remarks": ""
        }
      ],
      "highest_selling_price": 0,
      "lowest_selling_price": 0,
      "price_sources": [
        {
          "reseller_name": "Placeholder Reseller",
          "price": 0,
          "last_updated": "2025-03-14"
        }
      ]
    }
  ],
  "strength": "",
  "form": "",
  "suppliers": [],
  "reseller_prices": {
    "highest_selling_price": 0,
    "lowest_selling_price": 0,
    "price_sources": []
  },
  "supplier_price": {
    "lowest_price": 0,
    "source": "Placeholder Source",
    "market_type": "Others",
    "custom_market_name": "",
    "last_updated": "2025-03-14",
    "remarks": ""
  },
  "price_updated_year": 2025
}