{
  "registration_no": "MAL19961153T",
  "product_name": "ZHONG GUO YEAN MIN CHIEW",
  "holder": "HAI-O ENTERPRISE BERHAD",
  "holder_address": "WISMA HAI-O, LOT 11995, \n, BATU 2, JALAN KAPAR, 41400, KLANG, MALAYSIA,",
  "manufacturer": "HUANGSHI SINMA WINERY",
  "manufacturer_address": "141,YAN AN ROAD, HUANGSHI,HUBEI,, CHINA,",
  "importer": "HAI-O ENTERPRISE BERHAD",
  "importer_address": "WISMA HAI-O, LOT 11995, \n, BATU 2, JALAN KAPAR, 41400, KLANG, MALAYSIA,",
  "active_ingredients": [
    "Cyathula officinalis",
    "Dipsacus asper",
    "Glycyrrhiza uralensis",
    "Lycium chinensis",
    "Paeonia lactiflora",
    "Panax ginseng",
    "Poria cocos",
    "Rhizoma Notopterygium incisum",
    "RHIZOMA LIGUSTICUM CHUANXIONG",
    "RADIX REHMANNIAE GLUTINOSA",
    "Radix Morinda Officinalis",
    "Radix Glehnia littoralis",
    "POLYGONATUM SIBIRICUM RHIZOMA",
    "PEUCEDANUM PRAERUPTORUM RADIX",
    "Pericarpium Citrus reticulata.",
    "Herbal Cistanche Deserticola",
    "HERBA EPIMEDIUM GRANDIFLORUM",
    "Fructus Ziziphus Jujuba",
    "flos syzgium aromaticum",
    "Flos Carthamus Tinctorius",
    "EUCOMMIA ULMMOIDES",
    "CORTEX FRAXINI/FRAXINUS RHYNCHOLPHYLLA",
    "CORTEX CINNAMOMUM CASSIA",
    "ARNEBIA EUCHROMA RADIX",
    "Ramulus Taxillus chinensis",
    "Radix Polygonum multiflorum"
  ],
  "sku": [
    {
      "package_description": "750ml mL",
      "sku_unit": "ml",
      "quantity_per_sku": 750,
      "base_cost": 0,
      "tier_pricing": [
        {
          "min_qty": 100,
          "cost_per_unit": 0,
          "source": "Placeholder Source",
          "market_type": "Others",
          "custom_market_name": "",
          "last_updated": "2025-03-14",
          "remarks": ""
        },
        {
          "min_qty": 500,
          "cost_per_unit": 0,
          "source": "Placeholder Source",
          "market_type": "Others",
          "custom_market_name": "",
          "last_updated": "2025-03-14",
          "remarks": ""
        }
      ],
      "highest_selling_price": 0,
      "lowest_selling_price": 0,
      "price_sources": [
        {
          "reseller_name": "Placeholder Reseller",
          "price": 0,
          "last_updated": "2025-03-14"
        }
      ]
    }
  ],
  "strength": "",
  "form": "",
  "suppliers": [],
  "reseller_prices": {
    "highest_selling_price": 0,
    "lowest_selling_price": 0,
    "price_sources": []
  },
  "supplier_price": {
    "lowest_price": 0,
    "source": "Placeholder Source",
    "market_type": "Others",
    "custom_market_name": "",
    "last_updated": "2025-03-14",
    "remarks": ""
  },
  "price_updated_year": 2025
}