{
  "registration_no": "MAL20040658T",
  "product_name": "YIN ONN PEARL GINSENG CORDYCEPS PLUS BAI FENG WAN",
  "holder": "HERBAL LAND MANUFACTURING SDN BHD",
  "holder_address": "15-21,  HALA PERUSAHAAN KLEDANG UTARA 2,, MENGLEMBU INDUSTRIAL PARK,, 31450, IPOH , MALAYSIA,",
  "manufacturer": "HERBAL LAND MANUFACTURING SDN BHD",
  "manufacturer_address": "15-21,  HALA PERUSAHAAN KLEDANG UTARA 2, MENGLEMBU INDUSTRIAL PARK, 31450, IPOH , MALAYSIA,",
  "importer": "",
  "importer_address": "",
  "active_ingredients": [
    "Citrus aurantium",
    "Poria cocos",
    "Sonchus asper",
    "COLLA CORII ASINI",
    "TRIGONELLA FRENUM-GRAECUM SEMEN",
    "SCUTELLARIA BAICALENSIS RADIX",
    "RHIZOMA NOTOPTERYGIUM FRANCHETII",
    "CYPERUS ROTUNDUS",
    "RHIZOMA ATRACTYLODIS MACROCEPHALAE",
    "REHMANNIA GLUTINOSA RHIZOMA",
    "radix paeonia lactiflora",
    "RADIX CODONOPSIS PILOSULAE",
    "Pearl Powder",
    "FRUCTUS AMOMUM VILLOSUM",
    "FOLIUM ARTEMISIA ARGYI",
    "CUSCUTA CHINENSIS SEMEN",
    "CORDYCEPS SINENSIS SACC.",
    "ASTRAGALUS HOANGTGHY",
    "ANGELICA POLYMORPHA RADIX",
    "Radix Glycyrrhiza Uralensis",
    "radix panax ginsen"
  ],
  "sku": [
    {
      "package_description": "10gm x 6 Units",
      "sku_unit": "g",
      "quantity_per_sku": 10,
      "base_cost": 0,
      "tier_pricing": [
        {
          "min_qty": 100,
          "cost_per_unit": 0,
          "source": "Placeholder Source",
          "market_type": "Others",
          "custom_market_name": "",
          "last_updated": "2025-03-14",
          "remarks": ""
        },
        {
          "min_qty": 500,
          "cost_per_unit": 0,
          "source": "Placeholder Source",
          "market_type": "Others",
          "custom_market_name": "",
          "last_updated": "2025-03-14",
          "remarks": ""
        }
      ],
      "highest_selling_price": 0,
      "lowest_selling_price": 0,
      "price_sources": [
        {
          "reseller_name": "Placeholder Reseller",
          "price": 0,
          "last_updated": "2025-03-14"
        }
      ]
    },
    {
      "package_description": "10gm x 2 Units",
      "sku_unit": "g",
      "quantity_per_sku": 10,
      "base_cost": 0,
      "tier_pricing": [
        {
          "min_qty": 100,
          "cost_per_unit": 0,
          "source": "Placeholder Source",
          "market_type": "Others",
          "custom_market_name": "",
          "last_updated": "2025-03-14",
          "remarks": ""
        },
        {
          "min_qty": 500,
          "cost_per_unit": 0,
          "source": "Placeholder Source",
          "market_type": "Others",
          "custom_market_name": "",
          "last_updated": "2025-03-14",
          "remarks": ""
        }
      ],
      "highest_selling_price": 0,
      "lowest_selling_price": 0,
      "price_sources": [
        {
          "reseller_name": "Placeholder Reseller",
          "price": 0,
          "last_updated": "2025-03-14"
        }
      ]
    },
    {
      "package_description": "10gm x 3 Units",
      "sku_unit": "g",
      "quantity_per_sku": 10,
      "base_cost": 0,
      "tier_pricing": [
        {
          "min_qty": 100,
          "cost_per_unit": 0,
          "source": "Placeholder Source",
          "market_type": "Others",
          "custom_market_name": "",
          "last_updated": "2025-03-14",
          "remarks": ""
        },
        {
          "min_qty": 500,
          "cost_per_unit": 0,
          "source": "Placeholder Source",
          "market_type": "Others",
          "custom_market_name": "",
          "last_updated": "2025-03-14",
          "remarks": ""
        }
      ],
      "highest_selling_price": 0,
      "lowest_selling_price": 0,
      "price_sources": [
        {
          "reseller_name": "Placeholder Reseller",
          "price": 0,
          "last_updated": "2025-03-14"
        }
      ]
    },
    {
      "package_description": "10gm x 1 Units",
      "sku_unit": "g",
      "quantity_per_sku": 10,
      "base_cost": 0,
      "tier_pricing": [
        {
          "min_qty": 100,
          "cost_per_unit": 0,
          "source": "Placeholder Source",
          "market_type": "Others",
          "custom_market_name": "",
          "last_updated": "2025-03-14",
          "remarks": ""
        },
        {
          "min_qty": 500,
          "cost_per_unit": 0,
          "source": "Placeholder Source",
          "market_type": "Others",
          "custom_market_name": "",
          "last_updated": "2025-03-14",
          "remarks": ""
        }
      ],
      "highest_selling_price": 0,
      "lowest_selling_price": 0,
      "price_sources": [
        {
          "reseller_name": "Placeholder Reseller",
          "price": 0,
          "last_updated": "2025-03-14"
        }
      ]
    },
    {
      "package_description": "10gm x 6 Units",
      "sku_unit": "g",
      "quantity_per_sku": 10,
      "base_cost": 0,
      "tier_pricing": [
        {
          "min_qty": 100,
          "cost_per_unit": 0,
          "source": "Placeholder Source",
          "market_type": "Others",
          "custom_market_name": "",
          "last_updated": "2025-03-14",
          "remarks": ""
        },
        {
          "min_qty": 500,
          "cost_per_unit": 0,
          "source": "Placeholder Source",
          "market_type": "Others",
          "custom_market_name": "",
          "last_updated": "2025-03-14",
          "remarks": ""
        }
      ],
      "highest_selling_price": 0,
      "lowest_selling_price": 0,
      "price_sources": [
        {
          "reseller_name": "Placeholder Reseller",
          "price": 0,
          "last_updated": "2025-03-14"
        }
      ]
    }
  ],
  "strength": "",
  "form": "",
  "suppliers": [],
  "reseller_prices": {
    "highest_selling_price": 0,
    "lowest_selling_price": 0,
    "price_sources": []
  },
  "supplier_price": {
    "lowest_price": 0,
    "source": "Placeholder Source",
    "market_type": "Others",
    "custom_market_name": "",
    "last_updated": "2025-03-14",
    "remarks": ""
  },
  "price_updated_year": 2025
}